TCLIService/TCLIService.py
TCLIService/__init__.py
TCLIService/constants.py
TCLIService/ttypes.py
py_hive_iomete-2.1.5.dist-info/licenses/LICENSE
pyhive/__init__.py
pyhive/common.py
pyhive/exc.py
pyhive/hive.py
pyhive/presto.py
pyhive/sqlalchemy_hive.py
pyhive/sqlalchemy_iomete.py
pyhive/sqlalchemy_presto.py
pyhive/sqlalchemy_trino.py
pyhive/trino.py
py_hive_iomete-2.1.5.dist-info/METADATA
py_hive_iomete-2.1.5.dist-info/WHEEL
py_hive_iomete-2.1.5.dist-info/entry_points.txt
py_hive_iomete-2.1.5.dist-info/top_level.txt
py_hive_iomete-2.1.5.dist-info/RECORD
