Metadata-Version: 2.4
Name: py-hive-iomete
Version: 2.1.5
Summary: Python interface to iomete (Hive)
Home-page: https://github.com/iomete/py-hive-iomete
Author: Vusal Dadalov
Author-email: vusal@iomete.com
License: Apache License, Version 2.0
Classifier: Intended Audience :: Developers
Classifier: License :: OSI Approved :: Apache Software License
Classifier: Operating System :: OS Independent
Classifier: Topic :: Database :: Front-Ends
License-File: LICENSE
Requires-Dist: future
Requires-Dist: python-dateutil
Requires-Dist: thrift==0.22.0
Provides-Extra: sqlalchemy
Requires-Dist: sqlalchemy<=1.4.46,>=1.3.0; extra == "sqlalchemy"
Provides-Extra: test
Requires-Dist: mock>=1.0.0; extra == "test"
Requires-Dist: pytest; extra == "test"
Requires-Dist: pytest-cov; extra == "test"
Requires-Dist: requests>=1.0.0; extra == "test"
Requires-Dist: sqlalchemy<=1.4.46,>=1.3.0; extra == "test"
Requires-Dist: thrift==0.22.0; extra == "test"
Provides-Extra: presto
Requires-Dist: requests>=1.0.0; extra == "presto"
Provides-Extra: trino
Requires-Dist: requests>=1.0.0; extra == "trino"
Provides-Extra: hive
Requires-Dist: sasl>=0.2.1; extra == "hive"
Requires-Dist: thrift>=0.10.0; extra == "hive"
Requires-Dist: thrift_sasl>=0.1.0; extra == "hive"
Provides-Extra: kerberos
Requires-Dist: requests_kerberos>=0.12.0; extra == "kerberos"
Dynamic: author
Dynamic: author-email
Dynamic: classifier
Dynamic: description
Dynamic: home-page
Dynamic: license
Dynamic: license-file
Dynamic: provides-extra
Dynamic: requires-dist
Dynamic: summary
